[
    {
        "username": "سید پارسا حسینی خواه",
        "password": "9123619138",
        "group": "A",
        "watchedVideos": []
    },
    {
        "username": "حسین حسین زاده",
        "password": "9125149395",
        "group": "A",
        "watchedVideos": []
    },
    {
        "username": "آرشام عبدالمجیدی",
        "password": "9219857338",
        "group": "B",
        "watchedVideos": []
    },
    {
        "username": "آرتین یوسفی",
        "password": "9026457160",
        "group": "B",
        "watchedVideos": []
    },
    {
        "username": "کارن سلطانیان",
        "password": "9961337614",
        "group": "B",
        "watchedVideos": []
    },
    {
        "username": "محمدامین مدنی محمدی",
        "password": "9107354365",
        "group": "A",
        "watchedVideos": []
    },
    {
        "username": "فرهام فروغي مقدم",
        "password": "9372045255",
        "group": "B",
        "watchedVideos": []
    },
    {
        "username": "محمد علی رضوی ذوالبین",
        "password": "9352334355",
        "group": "B",
        "watchedVideos": []
    },
    {
        "username": "ایمان پهلوان",
        "password": "9914553261",
        "group": "A",
        "watchedVideos": []
    },
    {
        "username": "برسام صبوری",
        "password": "9365534326",
        "group": "A",
        "watchedVideos": []
    },
    {
        "username": "رضا راستی",
        "password": "9169979923",
        "group": "A",
        "watchedVideos": []
    },
    {
        "username": "آرمان محمدی",
        "password": "9193253951",
        "group": "B",
        "watchedVideos": []
    },
    {
        "username": "محمد داودی",
        "password": "9942663004",
        "group": "A",
        "watchedVideos": []
    },
    {
        "username": "پرهام بدری",
        "password": "9027522532",
        "group": "A",
        "watchedVideos": []
    },
    {
        "username": "بردیا جعفری",
        "password": "9011066240",
        "group": "A",
        "watchedVideos": []
    },
    {
        "username": "آرشا نوروزی",
        "password": "9370212002",
        "group": "A",
        "watchedVideos": []
    },
    {
        "username": "رادین چاره طلب",
        "password": "9102364530",
        "group": "B",
        "watchedVideos": []
    },
    {
        "username": "محمدعرفان عبایی",
        "password": "9355687761",
        "group": "B",
        "watchedVideos": []
    }
]